<?xml version="1.0" encoding="utf-8"?>
<projectSettings>
  <projectSetting name="com.google.external-dependency-managerAnalyticsCookie" value="175b2791f2c940c69d9e289a4ded3705" />
  <projectSetting name="com.google.external-dependency-managerAnalyticsEnabled" value="True" />
  <projectSetting name="com.google.firebaseAnalyticsCookie" value="fa2c139c076b403399bf2217fff621e0" />
  <projectSetting name="com.google.firebaseAnalyticsEnabled" value="True" />
  <projectSetting name="Google.IOSResolver.VerboseLoggingEnabled" value="False" />
  <projectSetting name="Google.PackageManagerResolver.VerboseLoggingEnabled" value="False" />
  <projectSetting name="Google.VersionHandler.VerboseLoggingEnabled" value="True" />
  <projectSetting name="Google.VersionHandler.VersionHandlingEnabled" value="True" />
  <projectSetting name="GooglePlayServices.PromptBeforeAutoResolution" value="False" />
  <projectSetting name="GooglePlayServices.UseJetifier" value="True" />
</projectSettings>